nomeroff_net/__init__.py
nomeroff_net/data_loaders/__init__.py
nomeroff_net/data_loaders/img_generator.py
nomeroff_net/data_loaders/img_orientation_generator_from_np.py
nomeroff_net/data_loaders/img_orientation_generator_from_orig.py
nomeroff_net/data_loaders/text_image_generator.py
nomeroff_net/data_modules/__init__.py
nomeroff_net/data_modules/numberplate_ocr_data_module.py
nomeroff_net/data_modules/numberplate_options_data_module.py
nomeroff_net/data_modules/numberplate_orientation_data_module.py
nomeroff_net/image_loaders/__init__.py
nomeroff_net/image_loaders/base.py
nomeroff_net/image_loaders/dumpy_loader.py
nomeroff_net/image_loaders/opencv_loader.py
nomeroff_net/image_loaders/pillow_loader.py
nomeroff_net/image_loaders/turbo_loader.py
nomeroff_net/nnmodels/__init__.py
nomeroff_net/nnmodels/numberplate_classification_model.py
nomeroff_net/nnmodels/numberplate_count_line_model.py
nomeroff_net/nnmodels/numberplate_options_model.py
nomeroff_net/nnmodels/numberplate_orientation_model.py
nomeroff_net/nnmodels/numberplate_region_model.py
nomeroff_net/nnmodels/ocr_model.py
nomeroff_net/pipelines/__init__.py
nomeroff_net/pipelines/base.py
nomeroff_net/pipelines/number_plate_classification.py
nomeroff_net/pipelines/number_plate_classification_trt.py
nomeroff_net/pipelines/number_plate_detection_and_reading.py
nomeroff_net/pipelines/number_plate_detection_and_reading_runtime.py
nomeroff_net/pipelines/number_plate_detection_and_reading_trt.py
nomeroff_net/pipelines/number_plate_detection_and_reading_trt_runtime.py
nomeroff_net/pipelines/number_plate_filling.py
nomeroff_net/pipelines/number_plate_key_points_cropping.py
nomeroff_net/pipelines/number_plate_localization.py
nomeroff_net/pipelines/number_plate_localization_trt.py
nomeroff_net/pipelines/number_plate_text_reading.py
nomeroff_net/pipelines/number_plate_text_reading_trt.py
nomeroff_net/pipelines/number_plate_upscaling.py
nomeroff_net/pipes/__init__.py
nomeroff_net/pipes/number_plate_classificators/__init__.py
nomeroff_net-4.0.1.dist-info/LICENSE
nomeroff_net-4.0.1.dist-info/METADATA
nomeroff_net-4.0.1.dist-info/WHEEL
nomeroff_net-4.0.1.dist-info/dependency_links.txt
nomeroff_net-4.0.1.dist-info/top_level.txt
nomeroff_net-4.0.1.dist-info/RECORD
