Metadata-Version: 2.1
Name: nomeroff-net
Version: 4.0.1
Summary: Automatic numberplate recognition system
Home-page: https://github.com/ria-com/nomeroff-net
Author: Dmytro Probachay, Oleg Cherniy
Author-email: dimabendera@gmail.com, oleg.cherniy@ria.com
License: GNU General Public License v3.0
Keywords: ai nomeroffnet yolo11 yolov8 ocr rnn opensource license number plate recognition licenseplate numberplate license-plate number-plate ria-com ria.com ria
Classifier: Programming Language :: Python :: 3
Classifier: License :: OSI Approved :: GNU General Public License v3 (GPLv3)
Classifier: Operating System :: OS Independent
Classifier: Topic :: Scientific/Engineering :: Artificial Intelligence
Requires-Python: >=3.9
License-File: LICENSE
Requires-Dist: cython
Requires-Dist: setuptools
Requires-Dist: numpy
Requires-Dist: opencv-python
Requires-Dist: scikit-image
Requires-Dist: asyncio
Requires-Dist: gitpython
Requires-Dist: pycocotools
Requires-Dist: ujson
Requires-Dist: pillow
Requires-Dist: tqdm
Requires-Dist: matplotlib
Requires-Dist: scipy
Requires-Dist: torch >=1.12
Requires-Dist: torchvision >=0.13
Requires-Dist: PyYAML >=5.4
Requires-Dist: seaborn
Requires-Dist: pytorch-lightning ==1.8.6
Requires-Dist: ipywidgets
Requires-Dist: gevent
Requires-Dist: termcolor
Requires-Dist: scikit-learn
Requires-Dist: ultralytics >=8.3.12
Requires-Dist: albumentations
